MANIFEST.in
README
setup.py
Products/__init__.py
Products.Calendaring.egg-info/PKG-INFO
Products.Calendaring.egg-info/SOURCES.txt
Products.Calendaring.egg-info/dependency_links.txt
Products.Calendaring.egg-info/namespace_packages.txt
Products.Calendaring.egg-info/not-zip-safe
Products.Calendaring.egg-info/requires.txt
Products.Calendaring.egg-info/top_level.txt
Products/Calendaring/TODO
Products/Calendaring/__init__.py
Products/Calendaring/common.py
Products/Calendaring/config.py
Products/Calendaring/makefile.in
Products/Calendaring/marshaller.py
Products/Calendaring/refresh.txt
Products/Calendaring/tool.gif
Products/Calendaring/zopeevents.py
Products/Calendaring/Extensions/Install.py
Products/Calendaring/Extensions/__init__.py
Products/Calendaring/content/__init__.py
Products/Calendaring/content/calendar.py
Products/Calendaring/interface/__init__.py
Products/Calendaring/interface/model.py
Products/Calendaring/locales/calendaring.pot
Products/Calendaring/locales/de/LC_MESSAGES/calendaring.po
Products/Calendaring/locales/es/LC_MESSAGES/calendaring.po
Products/Calendaring/locales/fr/LC_MESSAGES/calendaring.po
Products/Calendaring/plone_calendar/plone_calendar.py
Products/Calendaring/tests/__init__.py
Products/Calendaring/tests/export.txt
Products/Calendaring/tests/marshall.txt
Products/Calendaring/tests/test_content.py
Products/Calendaring/tests/test_functional.py
Products/Calendaring/tests/utils.py
Products/Calendaring/tests/data/example.ics
Products/Calendaring/tests/data/frisco.ics
Products/Calendaring/tests/data/ical.ics
Products/Calendaring/tests/data/korganizer.ics
Products/Calendaring/tests/data/no_dtend.ics
Products/Calendaring/tests/data/outlook1.ics
Products/Calendaring/tests/data/outlook2.ics
Products/Calendaring/tests/data/outlook3.ics
Products/Calendaring/tests/data/sunbird.ics
Products/Calendaring/tests/data/tasks.ics
Products/Calendaring/tools/__init__.py
Products/Calendaring/tools/calendar.py
docs/CONTRIBUTORS.txt
docs/COPYRIGHT.txt
docs/HISTORY.txt
docs/INSTALL.txt
docs/LICENSE.gpl