Metadata-Version: 1.0
Name: Products.Calendaring
Version: 0.5b1
Summary: An iCalendar marshaller for Marshall
Home-page: http://dist.enfoldsystems.com/catalog/calendaring
Author: Sidnei da Silva
Author-email: sidnei@enfoldsystems.com
License: UNKNOWN
Platform: UNKNOWN
Classifier: Framework :: Plone
Classifier: Programming Language :: Python
